.tox/typecheck/lib/python3.10/site-packages/polywrap_sys_config_bundle/embeds/file-system-resolver/wrap.info
.tox/typecheck/lib/python3.10/site-packages/polywrap_sys_config_bundle/embeds/file-system-resolver/wrap.wasm
.tox/typecheck/lib/python3.10/site-packages/polywrap_sys_config_bundle/embeds/http-resolver/wrap.info
.tox/typecheck/lib/python3.10/site-packages/polywrap_sys_config_bundle/embeds/http-resolver/wrap.wasm
.tox/typecheck/lib/python3.10/site-packages/polywrap_sys_config_bundle/embeds/ipfs-http-client/wrap.info
.tox/typecheck/lib/python3.10/site-packages/polywrap_sys_config_bundle/embeds/ipfs-http-client/wrap.wasm
.tox/typecheck/lib/python3.10/site-packages/polywrap_sys_config_bundle/embeds/ipfs-sync-resolver/wrap.info
.tox/typecheck/lib/python3.10/site-packages/polywrap_sys_config_bundle/embeds/ipfs-sync-resolver/wrap.wasm
polywrap_web3_config_bundle/__init__.py
polywrap_web3_config_bundle/bundle.py
polywrap_web3_config_bundle/py.typed
polywrap_web3_config_bundle-0.1.2.dist-info/METADATA
polywrap_web3_config_bundle-0.1.2.dist-info/WHEEL
polywrap_web3_config_bundle-0.1.2.dist-info/RECORD
